{
    "cards": [
        {
            "card_name": "СберКарта",
            "bank_name": "Сбербанк",
            "payment_system": "МИР",
            "credit_limit": "до 1 млн ₽",
            "interest_rate": null,
            "grace_period": "120 дней",
            "annual_fee": "Бесплатно",
            "cashback": null,
            "features": [
                "Бонусы за покупки",
                "Доставка курьером",
                "Бесплатные уведомления",
                "Без справок о доходах",
                "Для путешествий",
                "Оплата смартфоном MirAccept",
                "Бонусы в супермаркетах"
            ],
            "benefits": {
                "restaurants": null,
                "groceries": null,
                "travel": "Для путешествий",
                "entertainment": null,
                "online_shopping": null,
                "other": "Бонусы в супермаркетах"
            }
        },
        {
            "card_name": "Мир Classic",
            "bank_name": "Банк Уралсиб",
            "payment_system": "МИР",
            "credit_limit": "до 5 млн ₽",
            "interest_rate": null,
            "grace_period": "120 дней",
            "annual_fee": "Бесплатно",
            "cashback": null,
            "features": [
                "Бонусы за покупки",
                "Доставка курьером",
                "Наличные бесплатно",
                "Без справок о доходах",
                "Для путешествий",
                "Оплата смартфоном MirAccept"
            ],
            "benefits": {
                "restaurants": null,
                "groceries": null,
                "travel": "Для путешествий",
                "entertainment": null,
                "online_shopping": null,
                "other": null
            }
        },
        {
            "card_name": "СберКарта Молодёжная",
            "bank_name": "Сбербанк",
            "payment_system": "МИР",
            "credit_limit": "до 1 млн ₽",
            "interest_rate": null,
            "grace_period": "120 дней",
            "annual_fee": "Бесплатно",
            "cashback": null,
            "features": [
                "Бонусы за покупки",
                "Доставка курьером",
                "Бесплатные уведомления",
                "Без справок о доходах",
                "Для путешествий",
                "Оплата смартфоном MirAccept",
                "Бонусы в супермаркетах"
            ],
            "benefits": {
                "restaurants": null,
                "groceries": null,
                "travel": "Для путешествий",
                "entertainment": null,
                "online_shopping": null,
                "other": "Бонусы в супермаркетах"
            }
        },
        {
            "card_name": "Кредитная карта Альфа-Банка",
            "bank_name": "Альфа-Банк",
            "payment_system": "МИР",
            "credit_limit": "до 1 млн ₽",
            "interest_rate": null,
            "grace_period": "60 дней",
            "annual_fee": "от 0 до 990 ₽ в год",
            "cashback": null,
            "features": [
                "С кэшбеком",
                "Бонусы за покупки",
                "Доставка курьером",
                "Без справок о доходах",
                "Для путешествий",
                "Оплата смартфоном MirAccept",
                "Для самозанятых",
                "Платежный стикер"
            ],
            "benefits": {
                "restaurants": null,
                "groceries": null,
                "travel": "Для путешествий",
                "entertainment": null,
                "online_shopping": null,
                "other": null
            }
        },
        {
            "card_name": "Urban card",
            "bank_name": "Кредит Европа Банк (Россия)",
            "payment_system": "МИР",
            "credit_limit": "до 600 000 ₽",
            "interest_rate": null,
            "grace_period": "55 дней",
            "annual_fee": "Бесплатно",
            "cashback": "С кэшбеком",
            "features": [
                "Бонусы за покупки",
                "Доставка курьером",
                "Рассрочка",
                "Оплата смартфоном MirAccept",
                "Для самозанятых",
                "Бонусы на АЗС",
                "Бонусы на такси",
                "Платежный стикер"
            ],
            "benefits": {
                "restaurants": null,
                "groceries": null,
                "travel": null,
                "entertainment": null,
                "online_shopping": null,
                "other": "Бонусы на АЗС, Бонусы на такси"
            }
        },
        {
            "card_name": "Платинум",
            "bank_name": "Т-Банк",
            "payment_system": "МИР",
            "credit_limit": "до 1 млн ₽",
            "interest_rate": null,
            "grace_period": "55 дней",
            "annual_fee": "Бесплатно",
            "cashback": null,
            "features": [
                "Бонусы за покупки",
                "Доставка курьером",
                "Без справок о доходах",
                "Для путешествий",
                "Рассрочка",
                "Оплата смартфоном MirAccept",
                "Платежный стикер"
            ],
            "benefits": {
                "restaurants": null,
                "groceries": null,
                "travel": "Для путешествий",
                "entertainment": null,
                "online_shopping": null,
                "other": null
            }
        },
        {
            "card_name": "МТС Zero",
            "bank_name": "МТС Банк",
            "payment_system": "МИР",
            "credit_limit": "до 300 000 ₽",
            "interest_rate": null,
            "grace_period": "1 115 дней",
            "annual_fee": "от 0 до 2 370 ₽ в мес",
            "cashback": "С кэшбеком",
            "features": [
                "Бонусы за покупки",
                "Доставка курьером",
                "Наличные бесплатно",
                "Без справок о доходах",
                "Оплата смартфоном MirAccept",
                "Бонусы за медицинские услуги",
                "Платежный стикер"
            ],
            "benefits": {
                "restaurants": null,
                "groceries": null,
                "travel": null,
                "entertainment": null,
                "online_shopping": null,
                "other": "Бонусы за медицинские услуги"
            }
        },
        {
            "card_name": "Универсальная",
            "bank_name": "Азиатско-Тихоокеанский Банк",
            "payment_system": "VISA",
            "credit_limit": "до 500 000 ₽",
            "interest_rate": null,
            "grace_period": "212 дней",
            "annual_fee": "Бесплатно",
            "cashback": null,
            "features": [
                "Бонусы за покупки",
                "Наличные бесплатно",
                "Без справок о доходах",
                "Оплата смартфоном 3D Secure",
                "Для самозанятых"
            ],
            "benefits": {
                "restaurants": null,
                "groceries": null,
                "travel": null,
                "entertainment": null,
                "online_shopping": null,
                "other": null
            }
        },
        {
            "card_name": "Кредитная карта",
            "bank_name": "ПСБ",
            "payment_system": "МИР",
            "credit_limit": null,
            "interest_rate": null,
            "grace_period": "180 дней",
            "annual_fee": null,
            "cashback": null,
            "features": [],
            "benefits": {
                "restaurants": null,
                "groceries": null,
                "travel": null,
                "entertainment": null,
                "online_shopping": null,
                "other": null
            }
        }
    ]
}